AniPy/__init__.py
AniPy/base_models.py
AniPy/errors.py
AniPy/helper.py
AniPy/Anilist/__init__.py
AniPy/Anilist/get.py
AniPy/Anilist/models.py
AniPy/Anilist/search.py
ani.py-0.2.3.dist-info/METADATA
ani.py-0.2.3.dist-info/RECORD
ani.py-0.2.3.dist-info/WHEEL
ani.py-0.2.3.dist-info/top_level.txt
test/__init__.py
test/test_anilist.py
