Metadata-Version: 2.1
Name: ani.py
Version: 0.2.3
Summary: Python interface for anime APIs
Home-page: UNKNOWN
Author: Joel Widmer
Author-email: joel.widmer.wj@gmail.com
License: UNKNOWN
Platform: UNKNOWN
Classifier: Programming Language :: Python :: 3.6
Classifier: License :: OSI Approved :: MIT License
Classifier: Operating System :: OS Independent
Requires-Dist: requests
Requires-Dist: requests-toolbelt
